mimir_visualizer/__init__.py
mimir_visualizer/modify/__init__.py
mimir_visualizer/modify/compose.py
mimir_visualizer/modify/image.py
mimir_visualizer/modify/model.py
mimir_visualizer/visualize/__init__.py
mimir_visualizer/visualize/class_activations.py
mimir_visualizer/visualize/saliency.py
mimir_visualizer-0.0.6.dist-info/LICENSE
mimir_visualizer-0.0.6.dist-info/METADATA
mimir_visualizer-0.0.6.dist-info/WHEEL
mimir_visualizer-0.0.6.dist-info/top_level.txt
mimir_visualizer-0.0.6.dist-info/RECORD
