Metadata-Version: 2.1
Name: mimir-visualizer
Version: 0.0.6
Summary: Mimir's visualization module.
Home-page: https://github.com/stevenah/mimir-visualizer
Author: Steven Hicks
Author-email: steven@simula.no
License: UNKNOWN
Platform: UNKNOWN
Classifier: Programming Language :: Python :: 3
